importall/__init__.py
importall/__main__.py
importall/finder.py
importall/main.py
importall-0.2.1.dist-info/LICENSE
importall-0.2.1.dist-info/METADATA
importall-0.2.1.dist-info/WHEEL
importall-0.2.1.dist-info/entry_points.txt
importall-0.2.1.dist-info/top_level.txt
importall-0.2.1.dist-info/RECORD
