Metadata-Version: 2.1
Name: importall
Version: 0.2.1
Summary: Imports all importable files in a package
Home-page: https://github.com/python-packaging/importall/
Author: Tim Hatch
Author-email: tim@timhatch.com
License: MIT
Platform: UNKNOWN
Requires-Python: >=3.6
